datagent/__init__.py
datagent/sklearn_tools.py
datagent/statsmodels_tools.py
datagent-0.0.1.dist-info/licenses/LICENSE
datagent-0.0.1.dist-info/METADATA
datagent-0.0.1.dist-info/WHEEL
datagent-0.0.1.dist-info/top_level.txt
datagent-0.0.1.dist-info/RECORD
