Metadata-Version: 2.4
Name: datagent
Version: 0.0.1
Summary: A comprehensive data analysis toolkit with universal sklearn and statsmodels tools for LangGraph agents
Author-email: Haris Jabbar <haris@superpandas.ai>
Maintainer-email: Haris Jabbar <haris@superpandas.ai>
License: MIT
Project-URL: Homepage, https://github.com/superpandas-ai/datagent
Project-URL: Documentation, https://datagent.readthedocs.io/
Project-URL: Repository, https://github.com/superpandas-ai/datagent
Project-URL: Bug Tracker, https://github.com/superpandas-ai/datagent/issues
Keywords: machine-learning,scikit-learn,statsmodels,data-analysis,langgraph,langchain
Classifier: Development Status :: 4 - Beta
Classifier: Intended Audience :: Developers
Classifier: Intended Audience :: Science/Research
Classifier: License :: OSI Approved :: MIT License
Classifier: Operating System :: OS Independent
Classifier: Programming Language :: Python :: 3
Classifier: Programming Language :: Python :: 3.8
Classifier: Programming Language :: Python :: 3.9
Classifier: Programming Language :: Python :: 3.10
Classifier: Programming Language :: Python :: 3.11
Classifier: Topic :: Scientific/Engineering :: Artificial Intelligence
Classifier: Topic :: Scientific/Engineering :: Information Analysis
Classifier: Topic :: Software Development :: Libraries :: Python Modules
Requires-Python: >=3.8
License-File: LICENSE
Requires-Dist: statsmodels>=0.14.0
Requires-Dist: pandas>=1.5.0
Requires-Dist: numpy>=1.21.0
Requires-Dist: scipy>=1.9.0
Requires-Dist: scikit-learn>=1.1.0
Provides-Extra: dev
Requires-Dist: pytest>=7.0.0; extra == "dev"
Requires-Dist: pytest-cov>=4.0.0; extra == "dev"
Requires-Dist: pytest-mock>=3.10.0; extra == "dev"
Requires-Dist: pytest-html>=3.1.0; extra == "dev"
Requires-Dist: coverage>=7.0.0; extra == "dev"
Requires-Dist: black>=22.0.0; extra == "dev"
Requires-Dist: flake8>=5.0.0; extra == "dev"
Requires-Dist: mypy>=1.0.0; extra == "dev"
Provides-Extra: langgraph
Requires-Dist: langgraph>=0.1.0; extra == "langgraph"
Requires-Dist: langchain>=0.1.0; extra == "langgraph"
Dynamic: license-file
